Metadata-Version: 1.1
Name: django-jam
Version: 0.1
Summary: Front-end model admin views for Django
Home-page: https://bitbucket.org/mhurt/django-jam
Author: Mike Hurt
Author-email: mike@mhtechnical.net
License: MIT License
Platform: UNKNOWN
Classifier: Development Status :: 5 - Production/Stable
Classifier: Environment :: Web Environment
Classifier: Framework :: Django
Classifier: Intended Audience :: Developers
Classifier: License :: OSI Approved :: MIT License
Classifier: Operating System :: OS Independent
Classifier: Programming Language :: Python :: 2
Classifier: Programming Language :: Python :: 2.7
Classifier: Programming Language :: Python :: 3
Classifier: Programming Language :: Python :: 3.4
Classifier: Programming Language :: Python
